{"0,12": {"mod": "a,0", "ref": 0}, "1,11": {"mod": "a,1", "ref": 1}, "2,10": {"mod": "a,2", "ref": 2}, "3,10": {"mod": "a,3", "ref": 3}, "4,11": {"mod": "a,4", "ref": 4}, "10,6": {"mod": "c,6", "ref": 5}, "11,6": {"mod": "c,5", "ref": 6}, "21,11": {"mod": "d,0", "ref": 7}, "20,12": {"mod": "d,1", "ref": 8}, "19,13": {"mod": "d,2", "ref": 9}, "18,13": {"mod": "d,3", "ref": 10}, "17,12": {"mod": "d,4", "ref": 11}, "11,7": {"mod": "c,10", "ref": 12}, "9,6": {"mod": "c,7", "ref": 13}, "9,7": {"mod": "c,8", "ref": 14}, "10,8": {"mod": "c,9", "ref": 15}, "12,6": {"mod": "c,11", "ref": 16}, "13,6": {"mod": "c,12", "ref": 17}, "10,11": {"mod": "c,15", "ref": 18}, "9,9": {"mod": "c,13", "ref": 19}, "9,10": {"mod": "c,14", "ref": 20}, "8,6": {"mod": "a,15", "ref": 21}, "7,7": {"mod": "a,14", "ref": 22}, "6,8": {"mod": "a,13", "ref": 23}, "6,15": {"mod": "a,10", "ref": 24}, "7,16": {"mod": "a,11", "ref": 25}, "5,9": {"mod": "a,12", "ref": 26}, "5,10": {"mod": "a,5", "ref": 27}, "5,11": {"mod": "a,6", "ref": 28}, "5,12": {"mod": "a,7", "ref": 29}, "5,13": {"mod": "a,8", "ref": 30}, "5,14": {"mod": "a,9", "ref": 31}, "11,5": {"mod": "c,4", "ref": 32}, "12,4": {"mod": "c,3", "ref": 33}, "12,3": {"mod": "c,2", "ref": 34}, "11,2": {"mod": "c,1", "ref": 35}, "10,1": {"mod": "c,0", "ref": 36}, "12,16": {"mod": "b,5", "ref": 37}, "12,17": {"mod": "b,6", "ref": 38}, "11,17": {"mod": "b,7", "ref": 39}, "9,17": {"mod": "b,9", "ref": 40}, "10,17": {"mod": "b,8", "ref": 41}, "8,17": {"mod": "b,10", "ref": 42}, "16,12": {"mod": "d,10", "ref": 43}, "13,17": {"mod": "d,9", "ref": 44}, "14,7": {"mod": "d,15", "ref": 45}, "14,16": {"mod": "d,8", "ref": 46}, "15,8": {"mod": "d,14", "ref": 47}, "15,15": {"mod": "d,7", "ref": 48}, "16,9": {"mod": "d,13", "ref": 49}, "16,14": {"mod": "d,6", "ref": 50}, "16,10": {"mod": "d,12", "ref": 51}, "16,13": {"mod": "d,5", "ref": 52}, "16,11": {"mod": "d,11", "ref": 53}, "11,22": {"mod": "b,0", "ref": 54}, "11,12": {"mod": "b,15", "ref": 55}, "10,21": {"mod": "b,1", "ref": 56}, "12,13": {"mod": "b,14", "ref": 57}, "9,20": {"mod": "b,2", "ref": 58}, "12,14": {"mod": "b,13", "ref": 59}, "9,19": {"mod": "b,3", "ref": 60}, "11,15": {"mod": "b,12", "ref": 61}, "10,18": {"mod": "b,4", "ref": 62}, "10,16": {"mod": "b,11", "ref": 63}, "7,17": {"mod": "\r,1", "ref": 64}}